{"device":"","tstamp":"1663029711","type":"video_watch_detail","data":[{"person":6595,"gender":"female","age":"Young","tstamps_inCamera":[{"id_inCam":1,"tstamp_in":"1663029658","tstamp_out":"1663029711"}],"time_inCamera":52.7,"tstamps_watching":[{"id_watch":1,"tstamp_in":"1663029659","tstamp_out":"1663029660"},{"id_watch":2,"tstamp_in":"1663029667","tstamp_out":"1663029670"},{"id_watch":3,"tstamp_in":"1663029689","tstamp_out":"1663029691"},{"id_watch":4,"tstamp_in":"1663029708","tstamp_out":"1663029709"}],"time_watching":7.4,"distance":279.0}]}