{"device":"","tstamp":"1663079711","type":"video_watch_detail","data":[{"person":8692,"gender":"female","age":"Young","tstamps_inCamera":[{"id_inCam":1,"tstamp_in":"1663079482","tstamp_out":"1663079711"}],"time_inCamera":228.9,"tstamps_watching":[{"id_watch":1,"tstamp_in":"1663079485","tstamp_out":"1663079486"},{"id_watch":2,"tstamp_in":"1663079512","tstamp_out":"1663079514"},{"id_watch":3,"tstamp_in":"1663079540","tstamp_out":"1663079551"},{"id_watch":4,"tstamp_in":"1663079557","tstamp_out":"1663079570"},{"id_watch":5,"tstamp_in":"1663079645","tstamp_out":"1663079647"},{"id_watch":6,"tstamp_in":"1663079682","tstamp_out":"1663079688"}],"time_watching":35.4,"distance":125.2}]}